{
	"name": "sql_serverless_views",
	"properties": {
		"content": {
			"query": "-- Do this only once!\nCREATE DATABASE AdventureWorksLTServerless\n\n-- Change database\nUSE AdventureWorksLTServerless\nGO\n\n-- Create a separate schema (optional)\nCREATE SCHEMA SalesLTViews\nGO\n\n-- Create views for every tables, based on PARQUET format\nCREATE VIEW SalesLTViews.Address AS SELECT * FROM OPENROWSET(BULK 'https://datalake3mstaeetovkk4.dfs.core.windows.net/landing/adventureworkslt/tables/parquet/SalesLT.Address.parquet', FORMAT = 'PARQUET') AS [result]\nGO\nCREATE VIEW SalesLTViews.Customer AS SELECT * FROM OPENROWSET(BULK 'https://datalake3mstaeetovkk4.dfs.core.windows.net/landing/adventureworkslt/tables/parquet/SalesLT.Customer.parquet', FORMAT = 'PARQUET') AS [result]\nGO\nCREATE VIEW SalesLTViews.CustomerAddress AS SELECT * FROM OPENROWSET(BULK 'https://datalake3mstaeetovkk4.dfs.core.windows.net/landing/adventureworkslt/tables/parquet/SalesLT.CustomerAddress.parquet', FORMAT = 'PARQUET') AS [result]\nGO\nCREATE VIEW SalesLTViews.Product AS SELECT * FROM OPENROWSET(BULK 'https://datalake3mstaeetovkk4.dfs.core.windows.net/landing/adventureworkslt/tables/parquet/SalesLT.Product.parquet', FORMAT = 'PARQUET') AS [result]\nGO\nCREATE VIEW SalesLTViews.ProductCategory AS SELECT * FROM OPENROWSET(BULK 'https://datalake3mstaeetovkk4.dfs.core.windows.net/landing/adventureworkslt/tables/parquet/SalesLT.ProductCategory.parquet', FORMAT = 'PARQUET') AS [result]\nGO\nCREATE VIEW SalesLTViews.ProductDescription AS SELECT * FROM OPENROWSET(BULK 'https://datalake3mstaeetovkk4.dfs.core.windows.net/landing/adventureworkslt/tables/parquet/SalesLT.ProductDescription.parquet', FORMAT = 'PARQUET') AS [result]\nGO\nCREATE VIEW SalesLTViews.ProductModel AS SELECT * FROM OPENROWSET(BULK 'https://datalake3mstaeetovkk4.dfs.core.windows.net/landing/adventureworkslt/tables/parquet/SalesLT.ProductModel.parquet', FORMAT = 'PARQUET') AS [result]\nGO\nCREATE VIEW SalesLTViews.ProductModelProductDescription AS SELECT * FROM OPENROWSET(BULK 'https://datalake3mstaeetovkk4.dfs.core.windows.net/landing/adventureworkslt/tables/parquet/SalesLT.ProductModelProductDescription.parquet', FORMAT = 'PARQUET') AS [result]\nGO\nCREATE VIEW SalesLTViews.SalesOrderDetail AS SELECT * FROM OPENROWSET(BULK 'https://datalake3mstaeetovkk4.dfs.core.windows.net/landing/adventureworkslt/tables/parquet/SalesLT.SalesOrderDetail.parquet', FORMAT = 'PARQUET') AS [result]\nGO\nCREATE VIEW SalesLTViews.SalesOrderHeader AS SELECT * FROM OPENROWSET(BULK 'https://datalake3mstaeetovkk4.dfs.core.windows.net/landing/adventureworkslt/tables/parquet/SalesLT.SalesOrderHeader.parquet', FORMAT = 'PARQUET') AS [result]\nGO\n\n-- PLAYGROUND: Confirm data can be retrieved\nSELECT TOP 100 * FROM SalesLTViews.Address\nSELECT TOP 100 * FROM SalesLTViews.Customer\nSELECT TOP 100 * FROM SalesLTViews.CustomerAddress\nSELECT TOP 100 * FROM SalesLTViews.Product\nSELECT TOP 100 * FROM SalesLTViews.ProductCategory\nSELECT TOP 100 * FROM SalesLTViews.ProductDescription\nSELECT TOP 100 * FROM SalesLTViews.ProductModel\nSELECT TOP 100 * FROM SalesLTViews.ProductModelProductDescription\nSELECT TOP 100 * FROM SalesLTViews.SalesOrderDetail\nSELECT TOP 100 * FROM SalesLTViews.SalesOrderHeader\n",
			"metadata": {
				"language": "sql"
			},
			"currentConnection": {
				"databaseName": "AdventureWorksLTServerless",
				"poolName": "Built-in"
			},
			"resultLimit": 5000
		},
		"type": "SqlQuery"
	}
}